fix_plugin_azure/__init__.py
fix_plugin_azure/azure_client.py
fix_plugin_azure/collector.py
fix_plugin_azure/config.py
fix_plugin_azure/utils.py
fix_plugin_azure/resource/__init__.py
fix_plugin_azure/resource/authorization.py
fix_plugin_azure/resource/base.py
fix_plugin_azure/resource/compute.py
fix_plugin_azure/resource/containerservice.py
fix_plugin_azure/resource/cosmosdb.py
fix_plugin_azure/resource/keyvault.py
fix_plugin_azure/resource/machinelearning.py
fix_plugin_azure/resource/metrics.py
fix_plugin_azure/resource/microsoft_graph.py
fix_plugin_azure/resource/monitor.py
fix_plugin_azure/resource/mysql.py
fix_plugin_azure/resource/network.py
fix_plugin_azure/resource/postgresql.py
fix_plugin_azure/resource/security.py
fix_plugin_azure/resource/sql_server.py
fix_plugin_azure/resource/storage.py
fix_plugin_azure/resource/web.py
fixinventory_plugin_azure-4.2.0.dist-info/METADATA
fixinventory_plugin_azure-4.2.0.dist-info/WHEEL
fixinventory_plugin_azure-4.2.0.dist-info/entry_points.txt
fixinventory_plugin_azure-4.2.0.dist-info/top_level.txt
fixinventory_plugin_azure-4.2.0.dist-info/RECORD
